pypelinerr/__init__.py
pypelinerr/pypelinerr.py
tests/__init__.py
tests/test_pypelinerr.py
pypelinerr-0.0.6.dist-info/LICENSE
pypelinerr-0.0.6.dist-info/METADATA
pypelinerr-0.0.6.dist-info/WHEEL
pypelinerr-0.0.6.dist-info/top_level.txt
pypelinerr-0.0.6.dist-info/RECORD
