Metadata-Version: 2.1
Name: pypelinerr
Version: 0.0.6
Summary: A Railway pattern based pypeline package
Home-page: https://github.com/yoavabadi/pypelinerr
Author: Yoav Abadi
Author-email: yoavabadi@gmail.com
License: UNKNOWN
Platform: UNKNOWN
Classifier: Programming Language :: Python :: 3
Classifier: License :: OSI Approved :: MIT License
Classifier: Operating System :: OS Independent
Requires: schema
Requires-Python: >=3.6
License-File: LICENSE
